Workbook

Sheet Datos
A1: Seg Horario | B1: Hora de pedido | C1: Tipo de pedido | D1: Tipo de Establecimiento | E1: ID | F1: Doblete | G1: ID | H1: Monto | I1: TARIFA | J1: RAPPI RECOMPENSA | K1: PROPINA | L1: KM | M1: Fecha | N1: DIA | O1: DIA TEXTO | P1: MES | Q1: MES TEXTO | R1: EFECTIVO | S1: MONTO EFECTIVO | T1: Lluvia
A2: 4 | B2: 6:39 a. m. | C2: Restaurante | D2: Groovy Cookies | H2: 1910 | M2: 45863 | N2: =DAY(M2) -> 25 | O2: =TEXT(M2,"DDDD") -> viernes | P2: =MONTH(M2) -> 7 | Q2: =TEXT(M2,"MMMM") -> julio
A3: 4 | B3: 5:49 a. m. | C3: Restaurante | D3: Cümen Cümen | H3: 2350 | M3: 45863 | N3: =DAY(M3) -> 25 | O3: =TEXT(M3,"DDDD") -> viernes | P3: =MONTH(M3) -> 7 | Q3: =TEXT(M3,"MMMM") -> julio
A4: 1 | B4: 1:53 a. m. | C4: Restaurante | D4: ELC - McDonald's | H4: 2481 | M4: 45863 | N4: =DAY(M4) -> 25 | O4: =TEXT(M4,"DDDD") -> viernes | P4: =MONTH(M4) -> 7 | Q4: =TEXT(M4,"MMMM") -> julio
A5: 1 | B5: 1:37 a. m. | C5: Restaurante | D5: COL - McDonald's | H5: 2141 | M5: 45863 | N5: =DAY(M5) -> 25 | O5: =TEXT(M5,"DDDD") -> viernes | P5: =MONTH(M5) -> 7 | Q5: =TEXT(M5,"MMMM") -> julio
A6: 1 | B6: 1:21 a. m. | C6: Restaurante | D6: Tea Connection | H6: 3260 | M6: 45863 | N6: =DAY(M6) -> 25 | O6: =TEXT(M6,"DDDD") -> viernes | P6: =MONTH(M6) -> 7 | Q6: =TEXT(M6,"MMMM") -> julio
A7: 1 | B7: 1:11 a. m. | C7: Restaurante | D7: DIA Palermo | H7: 2610 | M7: 45863 | N7: =DAY(M7) -> 25 | O7: =TEXT(M7,"DDDD") -> viernes | P7: =MONTH(M7) -> 7 | Q7: =TEXT(M7,"MMMM") -> julio
A8: 1 | B8: 12:56 a. m. | C8: Restaurante | D8: DIA Envío Rápido | H8: 5475 | M8: 45863 | N8: =DAY(M8) -> 25 | O8: =TEXT(M8,"DDDD") -> viernes | P8: =MONTH(M8) -> 7 | Q8: =TEXT(M8,"MMMM") -> julio
A9: 5 | B9: 9:49 a. m. | C9: Restaurante | D9: Rock and Ribs | F9: Green Eat - Sinclair | H9: 3430 | I9: 2710 | K9: 600 | M9: 45866 | N9: =DAY(M9) -> 28 | O9: =TEXT(M9,"DDDD") -> lunes | P9: =MONTH(M9) -> 7 | Q9: =TEXT(M9,"MMMM") -> julio
A10: 5 | B10: 9:31 a. m. | C10: Super/Tienda | D10: PIZZA DATA | H10: 2960 | I10: 1400 | K10: 1500 | M10: 45866 | N10: =DAY(M10) -> 28 | O10: =TEXT(M10,"DDDD") -> lunes | P10: =MONTH(M10) -> 7 | Q10: =TEXT(M10,"MMMM") -> julio
A11: 5 | B11: 9:02 a. m. | C11: Super/Tienda | D11: DIA Envío Rápido, cerviño (523) | F11: DIA Envío Rápido, cerviño (523) | H11: 4710 | I11: 3250 | J11: 40 | K11: 1300 | M11: 45866 | N11: =DAY(M11) -> 28 | O11: =TEXT(M11,"DDDD") -> lunes | P11: =MONTH(M11) -> 7 | Q11: =TEXT(M11,"MMMM") -> julio
A12: 5 | B12: 8:29 a. m. | C12: Super/Tienda | D12: Carrefour Hiper, Salguero (6) | H12: 5100 | I12: 3540 | K12: 1460 | M12: 45866 | N12: =DAY(M12) -> 28 | O12: =TEXT(M12,"DDDD") -> lunes | P12: =MONTH(M12) -> 7 | Q12: =TEXT(M12,"MMMM") -> julio
A13: 5 | B13: 8:10 a. m. | C13: Super/Tienda | D13: Armando Florería | H13: 2030 | I13: 1220 | K13: 750 | M13: 45866 | N13: =DAY(M13) -> 28 | O13: =TEXT(M13,"DDDD") -> lunes | P13: =MONTH(M13) -> 7 | Q13: =TEXT(M13,"MMMM") -> julio
A14: 4 | B14: 6:51 a. m. | C14: Restaurante | D14: McDonald's - SF6 int | F14: McDonald's - SF6 int | H14: 2120 | I14: 1800 | K14: 200 | M14: 45866 | N14: =DAY(M14) -> 28 | O14: =TEXT(M14,"DDDD") -> lunes | P14: =MONTH(M14) -> 7 | Q14: =TEXT(M14,"MMMM") -> julio
A15: 4 | B15: 7:05 a. m. | C15: Restaurante | D15: Rappi Favor, Bs As CABA (Balvanera/Once) | H15: 1610 | M15: 45866 | N15: =DAY(M15) -> 28 | O15: =TEXT(M15,"DDDD") -> lunes | P15: =MONTH(M15) -> 7 | Q15: =TEXT(M15,"MMMM") -> julio
A16: 12 | B16: 10:36 p. m. | C16: Restaurante | D16: Los Maestros - recoleta | F16: Los Maestros - recoleta | H16: 3120 | M16: 45867 | N16: =DAY(M16) -> 29 | O16: =TEXT(M16,"DDDD") -> martes | P16: =MONTH(M16) -> 7 | Q16: =TEXT(M16,"MMMM") -> julio
A17: 12 | B17: 10:03 p. m. | C17: Super/Tienda | D17: Freddo - Ayacucho | H17: 1940 | I17: 1200 | K17: 680 | M17: 45867 | N17: =DAY(M17) -> 29 | O17: =TEXT(M17,"DDDD") -> martes | P17: =MONTH(M17) -> 7 | Q17: =TEXT(M17,"MMMM") -> julio
A18: 11 | B18: 8:58 p. m. | C18: Super/Tienda | D18: Rappi Favor, Bs As CABA (Villa Crespo/Chacarita) | H18: 1470 | I18: 1410 | J18: 60 | M18: 45867 | N18: =DAY(M18) -> 29 | O18: =TEXT(M18,"DDDD") -> martes | P18: =MONTH(M18) -> 7 | Q18: =TEXT(M18,"MMMM") -> julio
A19: 11 | B19: 8:27 p. m. | C19: Super/Tienda | D19: Faricci - Palermo | H19: 3400 | M19: 45867 | N19: =DAY(M19) -> 29 | O19: =TEXT(M19,"DDDD") -> martes | P19: =MONTH(M19) -> 7 | Q19: =TEXT(M19,"MMMM") -> julio
A20: 11 | B20: 8:18 p. m. | C20: Super/Tienda | D20: Tu Arepa Aguero | H20: 1260 | I20: 1200 | J20: 60 | M20: 45867 | N20: =DAY(M20) -> 29 | O20: =TEXT(M20,"DDDD") -> martes | P20: =MONTH(M20) -> 7 | Q20: =TEXT(M20,"MMMM") -> julio
A21: 9 | B21: 4:36 p. m. | C21: Restaurante | D21: Rincón Norteño - Parque Las Heras | H21: 2500 | I21: 1200 | K21: 1240 | M21: 45867 | N21: =DAY(M21) -> 29 | O21: =TEXT(M21,"DDDD") -> martes | P21: =MONTH(M21) -> 7 | Q21: =TEXT(M21,"MMMM") -> julio
A22: 9 | B22: 4:10 p. m. | C22: Super/Tienda | D22: Fullser24hs Palermo | H22: 1860 | I22: 1200 | K22: 600 | M22: 45867 | N22: =DAY(M22) -> 29 | O22: =TEXT(M22,"DDDD") -> martes | P22: =MONTH(M22) -> 7 | Q22: =TEXT(M22,"MMMM") -> julio
A23: 9 | B23: 7:37 p. m. | C23: Super/Tienda | D23: Coto, -158 Charcas | H23: 1260 | I23: 1200 | J23: 60 | M23: 45867 | N23: =DAY(M23) -> 29 | O23: =TEXT(M23,"DDDD") -> martes | P23: =MONTH(M23) -> 7 | Q23: =TEXT(M23,"MMMM") -> julio
A24: 9 | B24: 7:23 p. m. | C24: Restaurante | D24: Open Market, AV. Pueyrredon 1298 (964) | H24: 2360 | I24: 1200 | K24: 1100 | M24: 45867 | N24: =DAY(M24) -> 29 | O24: =TEXT(M24,"DDDD") -> martes | P24: =MONTH(M24) -> 7 | Q24: =TEXT(M24,"MMMM") -> julio
A25: 9 | B25: 6:47 p. m. | C25: Super/Tienda | D25: Cremolatti - Santa Fe | H25: 2820 | I25: 1200 | K25: 1560 | M25: 45867 | N25: =DAY(M25) -> 29 | O25: =TEXT(M25,"DDDD") -> martes | P25: =MONTH(M25) -> 7 | Q25: =TEXT(M25,"MMMM") -> julio
A26: 9 | B26: 6:33 p. m. | C26: Restaurante | D26: Coto, -158 Charcas | H26: 5850 | I26: 4700 | J26: 40 | K26: 1050 | M26: 45867 | N26: =DAY(M26) -> 29 | O26: =TEXT(M26,"DDDD") -> martes | P26: =MONTH(M26) -> 7 | Q26: =TEXT(M26,"MMMM") -> julio
A27: 8 | B27: 3:36 p. m. | C27: Super/Tienda | D27: Sake Sushi Delivery | H27: 2860 | I27: 1200 | K27: 1600 | M27: 45867 | N27: =DAY(M27) -> 29 | O27: =TEXT(M27,"DDDD") -> martes | P27: =MONTH(M27) -> 7 | Q27: =TEXT(M27,"MMMM") -> julio
A28: 8 | B28: 3:02 p. m. | C28: Super/Tienda | D28: Burgertify - Recoleta | H28: 2280 | I28: 1200 | K28: 1020 | M28: 45867 | N28: =DAY(M28) -> 29 | O28: =TEXT(M28,"DDDD") -> martes | P28: =MONTH(M28) -> 7 | Q28: =TEXT(M28,"MMMM") -> julio
A29: 8 | B29: 2:26 p. m. | C29: Restaurante | D29: SushiPop - Las Heras | H29: 2760 | I29: 1200 | K29: 1500 | M29: 45867 | N29: =DAY(M29) -> 29 | O29: =TEXT(M29,"DDDD") -> martes | P29: =MONTH(M29) -> 7 | Q29: =TEXT(M29,"MMMM") -> julio
A30: 7 | B30: 1:48 p. m. | C30: Restaurante | D30: The Food Truck - PALERMO | F30: Fabric Sushi Barrio Norte | H30: 2570 | I30: 2450 | M30: 45867 | N30: =DAY(M30) -> 29 | O30: =TEXT(M30,"DDDD") -> martes | P30: =MONTH(M30) -> 7 | Q30: =TEXT(M30,"MMMM") -> julio
A31: 11 | B31: 8:05 p.m. | C31: Panadería | D31: McDonald's - SF3 int | F31: McDonald's - SF3 int | H31: 1920 | I31: 1800 | M31: 45868 | N31: =DAY(M31) -> 30 | O31: =TEXT(M31,"DDDD") -> miércoles | P31: =MONTH(M31) -> 7 | Q31: =TEXT(M31,"MMMM") -> julio | R31: efectivo | S31: 19692
A32: 9 | B32: 6:11 p. m. | C32: Super/Tienda | D32: McDonald's - SF5 int | F32: McDonald's - SF5 int | H32: 2720 | I32: 2100 | K32: 500 | M32: 45868 | N32: =DAY(M32) -> 30 | O32: =TEXT(M32,"DDDD") -> miércoles | P32: =MONTH(M32) -> 7 | Q32: =TEXT(M32,"MMMM") -> julio
A33: 8 | B33: 5:50 p. m. | C33: Super/Tienda | D33: Turbo, Palermo 1 | H33: 2470 | I33: 2050 | K33: 360 | M33: 45868 | N33: =DAY(M33) -> 30 | O33: =TEXT(M33,"DDDD") -> miércoles | P33: =MONTH(M33) -> 7 | Q33: =TEXT(M33,"MMMM") -> julio
A34: 8 | B34: 5:20 p. m. | C34: Restaurante | D34: McDonald's - CPY int | H34: 2060 | I34: 1200 | K34: 800 | M34: 45868 | N34: =DAY(M34) -> 30 | O34: =TEXT(M34,"DDDD") -> miércoles | P34: =MONTH(M34) -> 7 | Q34: =TEXT(M34,"MMMM") -> julio
A35: 8 | B35: 4:54 p. m. | C35: Restaurante | D35: McDonald's - SF3 int | H35: 2640 | I35: 1200 | K35: 1380 | M35: 45868 | N35: =DAY(M35) -> 30 | O35: =TEXT(M35,"DDDD") -> miércoles | P35: =MONTH(M35) -> 7 | Q35: =TEXT(M35,"MMMM") -> julio | R35: efectivo | S35: 29719.5
A36: 8 | B36: 4:21 p. m. | C36: Super/Tienda | D36: McDonald's - SF3 int | H36: 2520 | I36: 1200 | K36: 1260 | M36: 45868 | N36: =DAY(M36) -> 30 | O36: =TEXT(M36,"DDDD") -> miércoles | P36: =MONTH(M36) -> 7 | Q36: =TEXT(M36,"MMMM") -> julio
A37: 9 | B37: 7:01 p.m. | C37: Super/Tienda | D37: KFC - Pueyrredón - Turbo | H37: 1960 | I37: 1200 | K37: 700 | M37: 45870 | N37: =DAY(M37) -> 1 | O37: =TEXT(M37,"DDDD") -> viernes | P37: =MONTH(M37) -> 8 | Q37: =TEXT(M37,"MMMM") -> agosto
A38: 9 | B38: 6:38 p.m. | C38: Restaurante | D38: Pan de Queso Brasil - Almagro | F38: Grido Once | H38: 3500 | I38: 2100 | K38: 1280 | M38: 45870 | N38: =DAY(M38) -> 1 | O38: =TEXT(M38,"DDDD") -> viernes | P38: =MONTH(M38) -> 8 | Q38: =TEXT(M38,"MMMM") -> agosto
A39: 9 | B39: 6:05 p.m. | C39: Restaurante | D39: Disco, Santa Fe(22) | H39: 3500 | I39: 2840 | K39: 600 | M39: 45870 | N39: =DAY(M39) -> 1 | O39: =TEXT(M39,"DDDD") -> viernes | P39: =MONTH(M39) -> 8 | Q39: =TEXT(M39,"MMMM") -> agosto
A40: 8 | B40: 5:46 p.m. | C40: Super/Tienda | D40: Coto, -158 Charcas | H40: 4400 | I40: 3680 | J40: 40 | K40: 620 | M40: 45870 | N40: =DAY(M40) -> 1 | O40: =TEXT(M40,"DDDD") -> viernes | P40: =MONTH(M40) -> 8 | Q40: =TEXT(M40,"MMMM") -> agosto
A41: 8 | B41: 4:08 p.m. | C41: Restaurante | D41: Kuono | H41: 3880 | I41: 2340 | K41: 1480 | M41: 45870 | N41: =DAY(M41) -> 1 | O41: =TEXT(M41,"DDDD") -> viernes | P41: =MONTH(M41) -> 8 | Q41: =TEXT(M41,"MMMM") -> agosto
A42: 7 | B42: 12:54 p.m. | C42: Super/Tienda | D42: Burger King - Bulnes | H42: 2860 | I42: 1200 | K42: 1600 | M42: 45870 | N42: =DAY(M42) -> 1 | O42: =TEXT(M42,"DDDD") -> viernes | P42: =MONTH(M42) -> 8 | Q42: =TEXT(M42,"MMMM") -> agosto
A43: 7 | B43: 12:14 p.m. | C43: Super/Tienda | D43: Haus Of Cookies | H43: 2610 | I43: 2050 | K43: 500 | M43: 45870 | N43: =DAY(M43) -> 1 | O43: =TEXT(M43,"DDDD") -> viernes | P43: =MONTH(M43) -> 8 | Q43: =TEXT(M43,"MMMM") -> agosto
A44: 7 | B44: 3:55 p.m. | C44: Super/Tienda | D44: Grido - Cnel. Diaz | F44: Burger King - Bulnes | H44: 3570 | I44: 2320 | K44: 1130 | M44: 45870 | N44: =DAY(M44) -> 1 | O44: =TEXT(M44,"DDDD") -> viernes | P44: =MONTH(M44) -> 8 | Q44: =TEXT(M44,"MMMM") -> agosto
A45: 7 | B45: 2:59 p.m. | C45: Restaurante | D45: McDonald's - AB2 | H45: 1860 | I45: 1200 | K45: 600 | M45: 45870 | N45: =DAY(M45) -> 1 | O45: =TEXT(M45,"DDDD") -> viernes | P45: =MONTH(M45) -> 8 | Q45: =TEXT(M45,"MMMM") -> agosto
A46: 7 | B46: 2:38 p.m. | C46: Restaurante | D46: MED - McDonald's Av Corrientes 3966 | H46: 1701 | I46: 1640 | K46: 1 | M46: 45870 | N46: =DAY(M46) -> 1 | O46: =TEXT(M46,"DDDD") -> viernes | P46: =MONTH(M46) -> 8 | Q46: =TEXT(M46,"MMMM") -> agosto
A47: 7 | B47: 2:26 p.m. | C47: Restaurante | D47: Burger Joint | H47: 3570 | I47: 1830 | K47: 1680 | M47: 45870 | N47: =DAY(M47) -> 1 | O47: =TEXT(M47,"DDDD") -> viernes | P47: =MONTH(M47) -> 8 | Q47: =TEXT(M47,"MMMM") -> agosto
A48: 7 | B48: 1:56 p.m. | C48: Super/Tienda | D48: El Club de la Milanesa Soho | H48: 3310 | I48: 1310 | K48: 1940 | M48: 45870 | N48: =DAY(M48) -> 1 | O48: =TEXT(M48,"DDDD") -> viernes | P48: =MONTH(M48) -> 8 | Q48: =TEXT(M48,"MMMM") -> agosto
A49: 6 | B49: 11:57 a.m. | C49: Restaurante | D49: Coto, 091-Abasto | H49: 2970 | I49: 2170 | J49: 40 | K49: 700 | M49: 45870 | N49: =DAY(M49) -> 1 | O49: =TEXT(M49,"DDDD") -> viernes | P49: =MONTH(M49) -> 8 | Q49: =TEXT(M49,"MMMM") -> agosto
A50: 6 | B50: 11:08 a.m. | C50: Super/Tienda | D50: Heladería Tino | H50: 2520 | I50: 2460 | M50: 45870 | N50: =DAY(M50) -> 1 | O50: =TEXT(M50,"DDDD") -> viernes | P50: =MONTH(M50) -> 8 | Q50: =TEXT(M50,"MMMM") -> agosto
A51: 6 | B51: 10:18 a.m. | C51: Restaurante | D51: Coto, 091-Abasto | H51: 3110 | I51: 2270 | K51: 780 | M51: 45870 | N51: =DAY(M51) -> 1 | O51: =TEXT(M51,"DDDD") -> viernes | P51: =MONTH(M51) -> 8 | Q51: =TEXT(M51,"MMMM") -> agosto
A52: 12 | B52: 10:23 p.m. | C52: Restaurante | D52: Maru Botana -Palermo | H52: 2380 | I52: 1640 | K52: 680 | M52: 45871 | N52: =DAY(M52) -> 2 | O52: =TEXT(M52,"DDDD") -> sábado | P52: =MONTH(M52) -> 8 | Q52: =TEXT(M52,"MMMM") -> agosto
A53: 12 | B53: 10:04 p.m. | C53: Super/Tienda | D53: El Peruanito Ray | H53: 4050 | I53: 1990 | K53: 2000 | M53: 45871 | N53: =DAY(M53) -> 2 | O53: =TEXT(M53,"DDDD") -> sábado | P53: =MONTH(M53) -> 8 | Q53: =TEXT(M53,"MMMM") -> agosto
A54: 11 | B54: 9:49 p.m. | C54: Restaurante | D54: John John Burger - Mario Bravo | H54: 4780 | I54: 2220 | K54: 2500 | M54: 45871 | N54: =DAY(M54) -> 2 | O54: =TEXT(M54,"DDDD") -> sábado | P54: =MONTH(M54) -> 8 | Q54: =TEXT(M54,"MMMM") -> agosto
A55: 11 | B55: 9:34 p.m. | C55: Restaurante | D55: DIA Envío Rápido, Almagro | F55: Craft Vegan Bakery, Palermo | H55: 6670 | I55: 4910 | J55: 40 | K55: 1600 | M55: 45871 | N55: =DAY(M55) -> 2 | O55: =TEXT(M55,"DDDD") -> sábado | P55: =MONTH(M55) -> 8 | Q55: =TEXT(M55,"MMMM") -> agosto
A56: 11 | B56: 9:03 p.m. | C56: Restaurante | D56: La Dorita - Botánico | H56: 3160 | I56: 1200 | K56: 1900 | M56: 45871 | N56: =DAY(M56) -> 2 | O56: =TEXT(M56,"DDDD") -> sábado | P56: =MONTH(M56) -> 8 | Q56: =TEXT(M56,"MMMM") -> agosto
A57: 11 | B57: 8:38 p.m. | C57: Restaurante | D57: Izakaya By Sushi - Coronel Diaz | F57: Dean & Dennys - Barrio Norte | H57: 4830 | I57: 2520 | K57: 2190 | M57: 45871 | N57: =DAY(M57) -> 2 | O57: =TEXT(M57,"DDDD") -> sábado | P57: =MONTH(M57) -> 8 | Q57: =TEXT(M57,"MMMM") -> agosto
A58: 10 | B58: 7:31 p.m. | C58: Restaurante | D58: Mickys Burgers | H58: 3490 | I58: 2590 | K58: 840 | M58: 45871 | N58: =DAY(M58) -> 2 | O58: =TEXT(M58,"DDDD") -> sábado | P58: =MONTH(M58) -> 8 | Q58: =TEXT(M58,"MMMM") -> agosto
A59: 10 | B59: 7:02 p.m. | C59: Restaurante | D59: Romario - Cañitas | F59: Romario - Cañitas | H59: 6250 | I59: 3190 | K59: 2940 | M59: 45871 | N59: =DAY(M59) -> 2 | O59: =TEXT(M59,"DDDD") -> sábado | P59: =MONTH(M59) -> 8 | Q59: =TEXT(M59,"MMMM") -> agosto
A60: 10 | B60: 6:48 p.m. | C60: Pago Manual | D60: La Payada - Palermo | H60: 3040 | I60: 1500 | K60: 1480 | M60: 45871 | N60: =DAY(M60) -> 2 | O60: =TEXT(M60,"DDDD") -> sábado | P60: =MONTH(M60) -> 8 | Q60: =TEXT(M60,"MMMM") -> agosto
A61: 10 | B61: 6:15 p.m. | C61: Restaurante | D61: Burger Couple - La Cupeteria | H61: 3340 | I61: 2080 | K61: 1200 | M61: 45871 | N61: =DAY(M61) -> 2 | O61: =TEXT(M61,"DDDD") -> sábado | P61: =MONTH(M61) -> 8 | Q61: =TEXT(M61,"MMMM") -> agosto
A62: 8 | B62: 3:08 p.m. | C62: Restaurante | D62: Open Market, AV santa Fe 3219 (935) | F62: Jevi, av. Santa Fe 3152 | H62: 2960 | I62: 2100 | K62: 740 | M62: 45871 | N62: =DAY(M62) -> 2 | O62: =TEXT(M62,"DDDD") -> sábado | P62: =MONTH(M62) -> 8 | Q62: =TEXT(M62,"MMMM") -> agosto
A63: 8 | B63: 2:49 p.m. | C63: Restaurante | D63: Postres McDonald's - CHE | H63: 1580 | I63: 1200 | K63: 320 | M63: 45871 | N63: =DAY(M63) -> 2 | O63: =TEXT(M63,"DDDD") -> sábado | P63: =MONTH(M63) -> 8 | Q63: =TEXT(M63,"MMMM") -> agosto
A64: 8 | B64: 2:29 p.m. | C64: Super/Tienda | D64: McDonald's - CHE | F64: McDonald's - CHE | H64: 4060 | I64: 1800 | K64: 2140 | M64: 45871 | N64: =DAY(M64) -> 2 | O64: =TEXT(M64,"DDDD") -> sábado | P64: =MONTH(M64) -> 8 | Q64: =TEXT(M64,"MMMM") -> agosto
A65: 8 | B65: 2:10 p.m. | C65: Super/Tienda | D65: CLH - McDonald's Av. Gral. Las Heras 3215 | H65: 1260 | I65: 1200 | M65: 45871 | N65: =DAY(M65) -> 2 | O65: =TEXT(M65,"DDDD") -> sábado | P65: =MONTH(M65) -> 8 | Q65: =TEXT(M65,"MMMM") -> agosto
A66: 7 | B66: 1:48 p.m. | C66: Super/Tienda | D66: McDonald's - SF3 int | H66: 1600 | I66: 1200 | K66: 340 | M66: 45871 | N66: =DAY(M66) -> 2 | O66: =TEXT(M66,"DDDD") -> sábado | P66: =MONTH(M66) -> 8 | Q66: =TEXT(M66,"MMMM") -> agosto
A67: 7 | B67: 1:47 p.m. | C67: Restaurante | D67: Salimos Fuerte, Plaza Italia | H67: 2420 | I67: 1200 | K67: 1160 | M67: 45871 | N67: =DAY(M67) -> 2 | O67: =TEXT(M67,"DDDD") -> sábado | P67: =MONTH(M67) -> 8 | Q67: =TEXT(M67,"MMMM") -> agosto
A68: 7 | B68: 1:27 p.m. | C68: Super/Tienda | D68: McDonald's - SF6 int | H68: 2380 | I68: 1200 | K68: 1120 | M68: 45871 | N68: =DAY(M68) -> 2 | O68: =TEXT(M68,"DDDD") -> sábado | P68: =MONTH(M68) -> 8 | Q68: =TEXT(M68,"MMMM") -> agosto
A69: 7 | B69: 1:03 p.m. | C69: Super/Tienda | D69: Dean & Dennys - palermo Pacifico | H69: 3080 | I69: 1200 | K69: 1820 | M69: 45871 | N69: =DAY(M69) -> 2 | O69: =TEXT(M69,"DDDD") -> sábado | P69: =MONTH(M69) -> 8 | Q69: =TEXT(M69,"MMMM") -> agosto
A70: 11 | B70: 9:35 p.m. | C70: Restaurante | D70: Burger King - Bulnes | F70: Burger King - Bulnes | H70: 3600 | I70: 2100 | K70: 1380 | M70: 45872 | N70: =DAY(M70) -> 3 | O70: =TEXT(M70,"DDDD") -> domingo | P70: =MONTH(M70) -> 8 | Q70: =TEXT(M70,"MMMM") -> agosto
A71: 11 | B71: 8:58 p.m. | C71: Restaurante | D71: Jevi, Av. Santa Fe 3152 | H71: 2760 | I71: 1200 | K71: 1500 | M71: 45872 | N71: =DAY(M71) -> 3 | O71: =TEXT(M71,"DDDD") -> domingo | P71: =MONTH(M71) -> 8 | Q71: =TEXT(M71,"MMMM") -> agosto
A72: 11 | B72: 8:29 p.m. | C72: Restaurante | D72: Chicken Chill - Pacifico | H72: 1760 | I72: 1700 | M72: 45872 | N72: =DAY(M72) -> 3 | O72: =TEXT(M72,"DDDD") -> domingo | P72: =MONTH(M72) -> 8 | Q72: =TEXT(M72,"MMMM") -> agosto
A73: 10 | B73: 7:50 p.m. | C73: Super/Tienda | D73: McDonald's - SF5 int | H73: 2760 | I73: 1200 | K73: 1500 | M73: 45872 | N73: =DAY(M73) -> 3 | O73: =TEXT(M73,"DDDD") -> domingo | P73: =MONTH(M73) -> 8 | Q73: =TEXT(M73,"MMMM") -> agosto
A74: 10 | B74: 6:44 p.m. | C74: Super/Tienda | D74: McDonald's - SF2 int | H74: 2060 | I74: 1200 | K74: 800 | M74: 45872 | N74: =DAY(M74) -> 3 | O74: =TEXT(M74,"DDDD") -> domingo | P74: =MONTH(M74) -> 8 | Q74: =TEXT(M74,"MMMM") -> agosto
A75: 9 | B75: 5:44 p.m. | C75: Restaurante | D75: Burger King Reina | H75: 3150 | I75: 1650 | K75: 1440 | M75: 45872 | N75: =DAY(M75) -> 3 | O75: =TEXT(M75,"DDDD") -> domingo | P75: =MONTH(M75) -> 8 | Q75: =TEXT(M75,"MMMM") -> agosto
A76: 9 | B76: 5:08 p.m. | C76: Super/Tienda | D76: McDonald's - SF6 int | H76: 2920 | M76: 45872 | N76: =DAY(M76) -> 3 | O76: =TEXT(M76,"DDDD") -> domingo | P76: =MONTH(M76) -> 8 | Q76: =TEXT(M76,"MMMM") -> agosto
A77: 9 | B77: 4:37 p.m. | C77: Super/Tienda | D77: Burger King - Bulnes | H77: 1760 | I77: 1200 | K77: 500 | M77: 45872 | N77: =DAY(M77) -> 3 | O77: =TEXT(M77,"DDDD") -> domingo | P77: =MONTH(M77) -> 8 | Q77: =TEXT(M77,"MMMM") -> agosto
A78: 8 | B78: 2:17 p.m. | C78: Restaurante | D78: McDonald's - SF6 int | H78: 1740 | I78: 1200 | K78: 480 | M78: 45872 | N78: =DAY(M78) -> 3 | O78: =TEXT(M78,"DDDD") -> domingo | P78: =MONTH(M78) -> 8 | Q78: =TEXT(M78,"MMMM") -> agosto
A79: 7 | B79: 1:50 p.m. | C79: Super/Tienda | D79: Pal Karajo | H79: 2320 | I79: 1320 | K79: 940 | M79: 45872 | N79: =DAY(M79) -> 3 | O79: =TEXT(M79,"DDDD") -> domingo | P79: =MONTH(M79) -> 8 | Q79: =TEXT(M79,"MMMM") -> agosto
A80: 9 | B80: 5:19 p.m. | C80: Super/Tienda | D80: Burger King - Once | H80: 2700 | I80: 1200 | K80: 1500 | M80: 45875 | N80: =DAY(M80) -> 6 | O80: =TEXT(M80,"DDDD") -> miércoles | P80: =MONTH(M80) -> 8 | Q80: =TEXT(M80,"MMMM") -> agosto
A81: 9 | B81: 5:00 p.m. | C81: Pago Manual | D81: Faricci - Palermo | H81: 2470 | I81: 2470 | M81: 45875 | N81: =DAY(M81) -> 6 | O81: =TEXT(M81,"DDDD") -> miércoles | P81: =MONTH(M81) -> 8 | Q81: =TEXT(M81,"MMMM") -> agosto | R81: efectivo | S81: 9312
A82: 3 | B82: 5:55 a.m. | C82: Restaurante | D82: McDonald's - SF5 int | F82: McDonald's - SF5 int | H82: 3860 | I82: 2220 | K82: 1640 | M82: 45875 | N82: =DAY(M82) -> 6 | O82: =TEXT(M82,"DDDD") -> miércoles | P82: =MONTH(M82) -> 8 | Q82: =TEXT(M82,"MMMM") -> agosto
A83: 3 | B83: 5:34 a.m. | C83: Restaurante | D83: Chévere Food | H83: 2040 | I83: 1200 | K83: 840 | M83: 45875 | N83: =DAY(M83) -> 6 | O83: =TEXT(M83,"DDDD") -> miércoles | P83: =MONTH(M83) -> 8 | Q83: =TEXT(M83,"MMMM") -> agosto
A84: 3 | B84: 5:14 a.m. | C84: Restaurante | D84: Chévere Food | H84: 1900 | I84: 1200 | K84: 700 | M84: 45875 | N84: =DAY(M84) -> 6 | O84: =TEXT(M84,"DDDD") -> miércoles | P84: =MONTH(M84) -> 8 | Q84: =TEXT(M84,"MMMM") -> agosto
A85: 2 | B85: 2:58 a.m. | C85: Restaurante | D85: McDonald's - SF3 int | H85: 1585 | I85: 1200 | K85: 385 | M85: 45875 | N85: =DAY(M85) -> 6 | O85: =TEXT(M85,"DDDD") -> miércoles | P85: =MONTH(M85) -> 8 | Q85: =TEXT(M85,"MMMM") -> agosto
A86: 2 | B86: 2:22 a.m. | C86: Super/Tienda | D86: KFC Pueyrredon | H86: 1200 | I86: 1200 | M86: 45875 | N86: =DAY(M86) -> 6 | O86: =TEXT(M86,"DDDD") -> miércoles | P86: =MONTH(M86) -> 8 | Q86: =TEXT(M86,"MMMM") -> agosto
A87: 2 | B87: 2:03 a.m. | C87: Restaurante | D87: The Best, Corrientes I | H87: 1320 | I87: 1220 | K87: 100 | M87: 45875 | N87: =DAY(M87) -> 6 | O87: =TEXT(M87,"DDDD") -> miércoles | P87: =MONTH(M87) -> 8 | Q87: =TEXT(M87,"MMMM") -> agosto | R87: efectivo | S87: 7565
A88: 1 | B88: 12:25 a.m. | C88: Restaurante | D88: Tufic | H88: 1290 | I88: 1290 | M88: 45875 | N88: =DAY(M88) -> 6 | O88: =TEXT(M88,"DDDD") -> miércoles | P88: =MONTH(M88) -> 8 | Q88: =TEXT(M88,"MMMM") -> agosto | R88: efectivo | S88: 22680
A89: 1 | B89: 12:07 a.m. | C89: Restaurante | D89: FarmaPlus, Barrio Norte | H89: 2150 | I89: 1250 | K89: 900 | M89: 45875 | N89: =DAY(M89) -> 6 | O89: =TEXT(M89,"DDDD") -> miércoles | P89: =MONTH(M89) -> 8 | Q89: =TEXT(M89,"MMMM") -> agosto
A90: 1 | B90: 1:32 a.m. | C90: Super/Tienda | D90: El King Bar Pool | H90: 2050 | I90: 1250 | K90: 800 | M90: 45875 | N90: =DAY(M90) -> 6 | O90: =TEXT(M90,"DDDD") -> miércoles | P90: =MONTH(M90) -> 8 | Q90: =TEXT(M90,"MMMM") -> agosto
A91: 1 | B91: 1:16 a.m. | C91: Super/Tienda | D91: McDonald's - CHE | H91: 1900 | I91: 1200 | K91: 700 | M91: 45875 | N91: =DAY(M91) -> 6 | O91: =TEXT(M91,"DDDD") -> miércoles | P91: =MONTH(M91) -> 8 | Q91: =TEXT(M91,"MMMM") -> agosto
A92: 1 | B92: 12:55 a.m. | C92: Super/Tienda | D92: Kremowy - Soler | H92: 2140 | I92: 1260 | K92: 880 | M92: 45875 | N92: =DAY(M92) -> 6 | O92: =TEXT(M92,"DDDD") -> miércoles | P92: =MONTH(M92) -> 8 | Q92: =TEXT(M92,"MMMM") -> agosto
A93: 4 | B93: 6:59 a.m. | C93: Super/Tienda | D93: La Mantequeria - Las Heras | H93: 1700 | I93: 1200 | K93: 500 | M93: 45877 | N93: =DAY(M93) -> 8 | O93: =TEXT(M93,"DDDD") -> viernes | P93: =MONTH(M93) -> 8 | Q93: =TEXT(M93,"MMMM") -> agosto
A94: 4 | B94: 6:33 a.m. | C94: Restaurante | D94: Burger King - Ayacucho | H94: 1700 | I94: 1200 | K94: 500 | M94: 45877 | N94: =DAY(M94) -> 8 | O94: =TEXT(M94,"DDDD") -> viernes | P94: =MONTH(M94) -> 8 | Q94: =TEXT(M94,"MMMM") -> agosto
A95: 3 | B95: 4:34 a.m. | C95: Restaurante | D95: Green Eat - Abasto Plaza | H95: 1740 | I95: 140 | K95: 500 | M95: 45877 | N95: =DAY(M95) -> 8 | O95: =TEXT(M95,"DDDD") -> viernes | P95: =MONTH(M95) -> 8 | Q95: =TEXT(M95,"MMMM") -> agosto | T95: 8
A96: 3 | B96: 4:04 a.m. | C96: Restaurante | D96: Rappi Favor, Bs As CABA (Microcentro) | H96: 1375 | I96: 1200 | K96: 175 | M96: 45877 | N96: =DAY(M96) -> 8 | O96: =TEXT(M96,"DDDD") -> viernes | P96: =MONTH(M96) -> 8 | Q96: =TEXT(M96,"MMMM") -> agosto
A97: 2 | B97: 3:28 a.m. | C97: Restaurante | D97: Las Medialunas | H97: 2320 | I97: 1200 | K97: 1120 | M97: 45877 | N97: =DAY(M97) -> 8 | O97: =TEXT(M97,"DDDD") -> viernes | P97: =MONTH(M97) -> 8 | Q97: =TEXT(M97,"MMMM") -> agosto
A98: 2 | B98: 3:42 p.m. | C98: Super/Tienda | D98: Guber Patisserie | H98: 1740 | I98: 1200 | K98: 540 | M98: 45877 | N98: =DAY(M98) -> 8 | O98: =TEXT(M98,"DDDD") -> viernes | P98: =MONTH(M98) -> 8 | Q98: =TEXT(M98,"MMMM") -> agosto
A99: 2 | B99: 2:56 p.m. | C99: Restaurante | D99: 354 - Express Carrefour Parana 1053 | H99: 1870 | I99: 1870 | M99: 45877 | N99: =DAY(M99) -> 8 | O99: =TEXT(M99,"DDDD") -> viernes | P99: =MONTH(M99) -> 8 | Q99: =TEXT(M99,"MMMM") -> agosto
A100: 2 | B100: 2:24 p.m. | C100: Super/Tienda | D100: Guber Patisserie Recoleta | H100: 1790 | I100: 1790 | M100: 45877 | N100: =DAY(M100) -> 8 | O100: =TEXT(M100,"DDDD") -> viernes | P100: =MONTH(M100) -> 8 | Q100: =TEXT(M100,"MMMM") -> agosto
...

Sheet Resumen_por_dia
A1: Fecha | B1: Total_Ingresos | C1: Cant_Pedidos | D1: DOBLETE | E1: Cantidad total Pedidios | F1: DIA | G1: Ticket_Promedio(No tiene en cuenta doblete) | I1: Seg Horario 1 | J1: Seg Horario 2 | K1: Seg Horario 3 | L1: Seg Horario 4 | M1: Seg Horario 5 | N1: Seg Horario 6 | O1: Seg Horario 7 | P1: Seg Horario 8 | Q1: Seg Horario 9 | R1: Seg Horario 10 | S1: Seg Horario 11 | T1: Seg Horario 12
A2: 45863 | B2: =SUM(Datos!H2:H8) -> 20227 | C2: =COUNTA(Datos!H2:H8) -> 7 | F2: Viernes | G2: =AVERAGE(Datos!H2:H8) -> 2889.5714 | I2: 1 | J2: 0 | K2: 0 | L2: 1 | M2: 0 | N2: 0 | O2: 0 | P2: 0 | Q2: 0 | R2: 0 | S2: 0 | T2: 0
A3: 45866 | B3: =SUM(Datos!H9:H15) -> 21960 | C3: =COUNTA(Datos!H9:H15) -> 7 | D3: 3 | E3: =SUM(C3+D3) -> 10 | F3: Lunes | G3: =AVERAGE(Datos!H9:H15) -> 3137.1429 | I3: 0 | J3: 0 | K3: 0 | L3: 1 | M3: 1 | N3: 0 | O3: 0 | P3: 0 | Q3: 0 | R3: 0 | S3: 0 | T3: 0
A4: 45867 | B4: =SUM(Datos!H16:H30) -> 38310 | C4: =COUNTA(Datos!H16:H30) -> 15 | D4: 2 | E4: =SUM(C4+D4) -> 17 | F4: Martes | G4: =AVERAGE(Datos!H16:H30) -> 2554 | I4: 0 | J4: 0 | K4: 0 | L4: 0 | M4: 0 | N4: 0 | O4: 1 | P4: 1 | Q4: 1 | R4: 0 | S4: 1 | T4: 1
A5: 45868 | B5: =SUM(Datos!H31:H36) -> 14330 | C5: =COUNTA(Datos!H31:H36) -> 6 | D5: 2 | E5: =SUM(C5+D5) -> 8 | F5: Miercoles | G5: =AVERAGE(Datos!H31:H36) -> 2388.3333 | I5: 0 | J5: 0 | K5: 0 | L5: 0 | M5: 0 | N5: 0 | O5: 0 | P5: 1 | Q5: 1 | R5: 0 | S5: 1 | T5: 0
A6: 45870 | B6: =SUM(Datos!H114:H128) -> 40900 | C6: =COUNTA(Datos!H114:H128) -> 15 | D6: 2 | E6: =SUM(C6+D6) -> 17 | F6: Viernes | G6: =AVERAGE(Datos!H114:H128) -> 2726.6667 | I6: 0 | J6: 0 | K6: 0 | L6: 0 | M6: 0 | N6: 1 | O6: 1 | P6: 1 | Q6: 1 | R6: 0 | S6: 0 | T6: 0
A7: 45871 | B7: =SUM(Datos!H52:H69) -> 61330 | C7: =COUNTA(Datos!H52:H69) -> 18 | D7: 5 | E7: =SUM(C7+D7) -> 23 | F7: Sabado | G7: =AVERAGE(Datos!H52:H69) -> 3407.2222 | I7: 0 | J7: 0 | K7: 0 | L7: 0 | M7: 0 | N7: 0 | O7: 0 | P7: 1 | Q7: 0 | R7: 1 | S7: 1 | T7: 1
A8: 45872 | B8: =SUM(Datos!H70:H79) -> 24830 | C8: =COUNTA(Datos!H70:H79) -> 10 | D8: 1 | E8: =SUM(C8+D8) -> 11 | F8: Domingo | G8: =AVERAGE(Datos!H70:H79) -> 2483 | I8: 0 | J8: 0 | K8: 0 | L8: 0 | M8: 0 | N8: 0 | O8: 1 | P8: 1 | Q8: 1 | R8: 1 | S8: 1 | T8: 0
A9: 45875 | B9: =SUM(Datos!H80:H92) -> 26605 | C9: =COUNTA(Datos!H80:H92) -> 13 | D9: 1 | E9: =SUM(C9+D9) -> 14 | F9: Miercoles | G9: =AVERAGE(Datos!H80:H92) -> 2046.5385 | I9: 1 | J9: 1 | K9: 1 | L9: 0 | M9: 0 | N9: 0 | O9: 0 | P9: 0 | Q9: 1 | R9: 0 | S9: 0 | T9: 0
A10: 45877 | B10: =SUM(Datos!H93:H101) -> 15435 | C10: =COUNTA(Datos!H93:H101) -> 9 | D10: 0 | E10: =SUM(C10+D10) -> 9 | F10: Viernes | G10: =AVERAGE(Datos!H93:H101) -> 1715 | I10: 1 | J10: 1 | K10: 1 | L10: 1 | M10: 0 | N10: 0 | O10: 0 | P10: 0 | Q10: 0 | R10: 0 | S10: 0 | T10: 0
A11: 45878 | B11: =SUM(Datos!H102:H116) -> 31841 | C11: =COUNTA(Datos!H102:H116) -> 15 | D11: 0 | E11: =SUM(C11+D11) -> 15 | F11: Sabado | G11: =AVERAGE(Datos!H102:H116) -> 2122.7333 | I11: 0 | J11: 0 | K11: 0 | L11: 0 | M11: 0 | N11: 0 | O11: 0 | P11: 0 | Q11: 1 | R11: 1 | S11: 1 | T11: 0
A12: 45879 | B12: =SUM(Datos!H117:H140) -> 61893.88 | C12: =COUNTA(Datos!H117:H140) -> 23 | D12: 6 | E12: =SUM(C12+D12) -> 29 | F12: Domingo | G12: =AVERAGE(Datos!H117:H140) -> 2691.0383 | I12: 1 | J12: 1 | K12: 1 | L12: 0 | M12: 0 | N12: 0 | O12: 0 | P12: 1 | Q12: 1 | R12: 1 | S12: 1 | T12: 1
A13: 45884 | B13: =SUM(Datos!H141:H150) -> 22640 | C13: =COUNTA(Datos!H141:H150) -> 10 | D13: 0 | E13: =SUM(C13+D13) -> 10 | F13: Viernes | G13: =AVERAGE(Datos!H141:H150) -> 2264 | I13: 0 | J13: 1 | K13: 0 | L13: 0 | M13: 0 | N13: 0 | O13: 0 | P13: 0 | Q13: 0 | R13: 0 | S13: 1 | T13: 1
A14: 45885 | B14: =SUM(Datos!H151:H157) -> 21470 | C14: =COUNTA(Datos!H151:H157) -> 7 | D14: 0 | E14: =SUM(C14+D14) -> 7 | F14: Sabado | G14: =AVERAGE(Datos!H151:H157) -> 3067.1429 | I14: 1 | J14: 1 | K14: 1 | L14: 0 | M14: 0 | N14: 0 | O14: 0 | P14: 0 | Q14: 0 | R14: 0 | S14: 0 | T14: 0
A15: 45889 | B15: =SUM(Datos!H158:H171) -> 33631 | C15: =COUNTA(Datos!H158:H171) -> 14 | D15: 0 | E15: =SUM(C15+D15) -> 14 | F15: Miercoles | G15: =AVERAGE(Datos!H158:H171) -> 2402.2143 | I15: 1 | J15: 1 | K15: 0 | L15: 0 | M15: 0 | N15: 0 | O15: 0 | P15: 0 | Q15: 1 | R15: 1 | S15: 0 | T15: 1
A16: 45890 | B16: =SUM(Datos!H172:H191) -> 42841 | C16: =COUNTA(Datos!H172:H191) -> 20 | D16: 0 | E16: =SUM(C16+D16) -> 20 | F16: Jueves | G16: =AVERAGE(Datos!H172:H191) -> 2142.05 | I16: 1 | J16: 1 | K16: 1 | L16: 0 | M16: 1 | N16: 1 | O16: 0 | P16: 0 | Q16: 1 | R16: 0 | S16: 1 | T16: 1
A17: 45893 | B17: =SUM(Datos!H192:H223) -> 99390 | C17: =COUNTA(Datos!H192:H223) -> 32 | D17: 7 | E17: =SUM(C17+D17) -> 39 | F17: Domingo | G17: =AVERAGE(Datos!H192:H223) -> 3105.9375 | I17: 0 | J17: 0 | K17: 0 | L17: 1 | M17: 1 | N17: 0 | O17: 1 | P17: 1 | Q17: 1 | R17: 1 | S17: 1 | T17: 1
A18: 45896 | B18: =SUM(Datos!H224:H239) -> 36375 | C18: =COUNTA(Datos!H224:H239) -> 16 | D18: 3 | E18: =SUM(C18+D18) -> 19 | F18: Miercoles | G18: =AVERAGE(Datos!H224:H239) -> 2273.4375 | I18: 0 | J18: 0 | K18: 0 | L18: 0 | M18: 0 | N18: 0 | O18: 0 | P18: 1 | Q18: 1 | R18: 1 | S18: 1 | T18: 1
A19: 45900 | B19: =SUM(Datos!H240:H255) -> 45700 | C19: =COUNTA(Datos!H240:H255) -> 16 | D19: 0 | E19: =SUM(C19+D19) -> 16 | F19: Domingo | G19: =AVERAGE(Datos!H240:H255) -> 2856.25 | I19: 0 | J19: 0 | K19: 1 | L19: 1 | M19: 0 | N19: 0 | O19: 1 | P19: 1 | Q19: 1 | R19: 1 | S19: 1 | T19: 0
A20: 45901 | B20: =SUM(Datos!H256:H264) -> 24670 | C20: =COUNTA(Datos!H256:H264) -> 9 | D20: 4 | E20: =SUM(C20+D20) -> 13 | F20: Lunes | G20: =AVERAGE(Datos!H256:H264) -> 2741.1111 | I20: 0 | J20: 0 | K20: 0 | L20: 0 | M20: 0 | N20: 0 | O20: 0 | P20: 1 | Q20: 1 | R20: 1 | S20: 0 | T20: 1
A21: 45902 | B21: =SUM(Datos!H265:H272) -> 19558 | C21: =COUNTA(Datos!H265:H272) -> 8 | D21: 1 | E21: =SUM(C21+D21) -> 9 | F21: Martes | G21: =AVERAGE(Datos!H265:H272) -> 2444.75 | I21: 1 | J21: 1 | K21: 1 | L21: 0 | M21: 0 | N21: 0 | O21: 0 | P21: 0 | Q21: 0 | R21: 0 | S21: 0 | T21: 0
A22: 45903 | B22: =SUM(Datos!H273:H280) -> 14536 | C22: =COUNTA(Datos!H273:H280) -> 8 | D22: 0 | E22: =SUM(C22+D22) -> 8 | F22: Miercoles | G22: =AVERAGE(Datos!H273:H280) -> 1817 | I22: 0 | J22: 0 | K22: 0 | L22: 0 | M22: 1 | N22: 1 | O22: 1 | P22: 0 | Q22: 0 | R22: 0 | S22: 0 | T22: 0
A23: 45904 | B23: =SUM(Datos!H281:H289) -> 16510 | C23: =COUNTA(Datos!H281:H289) -> 9 | D23: 2 | E23: =SUM(C23+D23) -> 11 | F23: Jueves | G23: =AVERAGE(Datos!H281:H289) -> 1834.4444 | I23: 0 | J23: 0 | K23: 0 | L23: 0 | M23: 0 | N23: 0 | O23: 0 | P23: 0 | Q23: 0 | R23: 1 | S23: 1 | T23: 1
A24: 45905 | B24: =SUM(Datos!H290:H297) -> 27510 | C24: =COUNTA(Datos!H290:H297) -> 8 | D24: 2 | E24: =SUM(C24+D24) -> 10 | F24: Viernes | G24: =AVERAGE(Datos!H290:H297) -> 3438.75 | I24: 0 | J24: 0 | K24: 0 | L24: 0 | M24: 0 | N24: 0 | O24: 0 | P24: 1 | Q24: 1 | R24: 1 | S24: 0 | T24: 1
A25: 45906 | B25: =SUM(Datos!H298:H308) -> 24060 | C25: =COUNTA(Datos!H298:H308) -> 11 | D25: 1 | E25: =SUM(C25+D25) -> 12 | F25: Sabado | G25: =AVERAGE(Datos!H298:H308) -> 2187.2727 | I25: 1 | J25: 1 | K25: 1 | L25: 0 | M25: 0 | N25: 0 | O25: 0 | P25: 0 | Q25: 0 | R25: 0 | S25: 0 | T25: 0
A26: 45907 | B26: =SUM(Datos!H309:H311) -> 7441 | C26: =COUNTA(Datos!H309:H311) -> 3 | D26: 2 | E26: =SUM(C26+D26) -> 5 | F26: Domingo | G26: =AVERAGE(Datos!H309:H311) -> 2480.3333 | I26: 0 | J26: 0 | K26: 0 | L26: 0 | M26: 0 | N26: 0 | O26: 0 | P26: 0 | Q26: 0 | R26: 0 | S26: 0 | T26: 1
A27: 45908 | B27: =SUM(Datos!H312:H316) -> 11320 | C27: =COUNTA(Datos!H312:H316) -> 5 | D27: 1 | E27: =SUM(C27+D27) -> 6 | F27: Lunes | G27: =AVERAGE(Datos!H312:H316) -> 2264 | I27: 1 | J27: 1 | K27: 0 | L27: 0 | M27: 0 | N27: 0 | O27: 0 | P27: 0 | Q27: 0 | R27: 0 | S27: 0 | T27: 0
A28: 45909 | B28: =SUM(Datos!H317:H322) -> 12850 | C28: =COUNTA(Datos!H317:H322) -> 6 | D28: 0 | E28: =SUM(C28+D28) -> 6 | F28: Martes | G28: =AVERAGE(Datos!H317:H322) -> 2141.6667 | I28: 0 | J28: 0 | K28: 0 | L28: 1 | M28: 1 | N28: 0 | O28: 0 | P28: 0 | Q28: 0 | R28: 0 | S28: 0 | T28: 0
A29: 45910 | B29: =SUM(Datos!H323:H331) -> 17690 | C29: =COUNTA(Datos!H323:H331) -> 9 | D29: 1 | E29: =SUM(C29+D29) -> 10 | F29: Miercoles | G29: =AVERAGE(Datos!H323:H331) -> 1965.5556 | I29: 0 | J29: 0 | K29: 0 | L29: 0 | M29: 0 | N29: 0 | O29: 0 | P29: 0 | Q29: 0 | R29: 1 | S29: 1 | T29: 1
A30: 45911 | B30: =SUM(Datos!H332:H338) -> 18790 | C30: =COUNTA(Datos!H332:H338) -> 7 | D30: 1 | E30: =SUM(C30+D30) -> 8 | F30: Jueves | G30: =AVERAGE(Datos!H332:H338) -> 2684.2857 | I30: 1 | J30: 0 | K30: 0 | L30: 0 | M30: 0 | N30: 0 | O30: 0 | P30: 0 | Q30: 0 | R30: 0 | S30: 0 | T30: 0
A31: 12//09/2025 | B31: =SUM(Datos!H339:H346) -> 22681 | C31: =COUNTA(Datos!H339:H346) -> 8 | D31: 5 | E31: =SUM(C31+D31) -> 13 | F31: Viernes | G31: =AVERAGE(Datos!H339:H346) -> 2835.125 | I31: 1 | J31: 1 | K31: 0 | L31: 0 | M31: 0 | N31: 0 | O31: 0 | P31: 0 | Q31: 0 | R31: 0 | S31: 0 | T31: 0
A32: 45914 | B32: =SUM(Datos!H347:H359) -> 32915 | C32: =COUNTA(Datos!H347:H359) -> 13 | D32: 1 | E32: =SUM(C32+D32) -> 14 | F32: Domingo | G32: =AVERAGE(Datos!H347:H359) -> 2531.9231 | I32: 0 | J32: 0 | K32: 0 | L32: 0 | M32: 1 | N32: 1 | O32: 1 | P32: 1 | Q32: 1 | R32: 0 | S32: 1 | T32: 0
A33: 45915 | B33: =SUM(Datos!H361:H361) -> 2580 | C33: =COUNTA(Datos!H361:H361) -> 1 | D33: 0 | E33: =SUM(C33+D33) -> 1 | F33: Lunes | G33: =AVERAGE(Datos!H361:H361) -> 2580 | I33: 0 | J33: 0 | K33: 0 | L33: 0 | M33: 0 | N33: 0 | O33: 1 | P33: 0 | Q33: 0 | R33: 0 | S33: 0 | T33: 0
A34: 45916 | B34: =SUM(Datos!H362:H374) -> 23715 | C34: =COUNTA(Datos!H362:H374) -> 13 | D34: 0 | E34: =SUM(C34+D34) -> 13 | F34: Martes | G34: =AVERAGE(Datos!H362:H374) -> 1824.2308 | I34: 0 | J34: 0 | K34: 0 | L34: 1 | M34: 1 | N34: 1 | O34: 1 | P34: 0 | Q34: 0 | R34: 0 | S34: 0 | T34: 0
A35: 45917 | B35: =SUM(Datos!H375:H382) -> 27001 | C35: =COUNTA(Datos!H375:H382) -> 8 | D35: 1 | E35: =SUM(C35+D35) -> 9 | F35: Miercoles | G35: =AVERAGE(Datos!H375:H382) -> 3375.125 | I35: 0 | J35: 0 | K35: 0 | L35: 0 | M35: 1 | N35: 1 | O35: 0 | P35: 0 | Q35: 0 | R35: 0 | S35: 0 | T35: 0
A36: 45918 | B36: =SUM(Datos!H383:H403) -> 49730 | C36: =COUNTA(Datos!H383:H403) -> 21 | D36: 4 | E36: =SUM(C36+D36) -> 25 | F36: Jueves | G36: =AVERAGE(Datos!H351:H363) -> 2400 | I36: 0 | J36: 0 | K36: 0 | L36: 1 | M36: 1 | N36: 1 | O36: 1 | P36: 1 | Q36: 1 | R36: 1 | S36: 1 | T36: 0
A37: 45919 | B37: =SUM(Datos!H404:H408) -> 15679 | C37: =COUNTA(Datos!H404:H408) -> 5 | D37: 2 | E37: =SUM(C37+D37) -> 7 | F37: Viernes | G37: =AVERAGE(Datos!H404:H408) -> 3135.8 | I37: 0 | J37: 0 | K37: 0 | L37: 0 | M37: 0 | N37: 0 | O37: 1 | P37: 1 | Q37: 0 | R37: 0 | S37: 0 | T37: 0
A38: 45920 | B38: =SUM(Datos!H409:H420) -> 45960 | C38: =COUNTA(Datos!H409:H420) -> 12 | D38: 2 | E38: =SUM(C38+D38) -> 14 | F38: Sabado | G38: =AVERAGE(Datos!H409:H420) -> 3830 | I38: 0 | J38: 0 | K38: 0 | L38: 0 | M38: 0 | N38: 0 | O38: 0 | P38: 0 | Q38: 1 | R38: 1 | S38: 1 | T38: 1
A39: 45924 | B39: =SUM(Datos!H421:H433) -> 32670 | C39: =COUNTA(Datos!H421:H433) -> 13 | D39: 4 | E39: =SUM(C39+D39) -> 17 | F39: Miercoles | G39: =AVERAGE(Datos!H421:H433) -> 2513.0769 | I39: 0 | J39: 0 | K39: 0 | L39: 0 | M39: 0 | N39: 0 | O39: 0 | P39: 0 | Q39: 1 | R39: 1 | S39: 1 | T39: 1
A40: 45926 | B40: =SUM(Datos!H434:H439) -> 9840 | C40: =COUNTA(Datos!H434:H439) -> 5 | D40: 0 | E40: =SUM(C40+D40) -> 5 | F40: =TEXT(A40,"DDDD") -> viernes | G40: =AVERAGE(Datos!H434:H439) -> 1968 | I40: 0 | J40: 0 | K40: 0 | L40: 0 | M40: 0 | N40: 0 | O40: 0 | P40: 1 | Q40: 1 | R40: 1 | S40: 1 | T40: 0
A41: 45928 | B41: =SUM(Datos!H440:H449) -> 35850 | C41: =COUNTA(Datos!H440:H449) -> 10 | D41: 2 | E41: =SUM(C41+D41) -> 12 | F41: =TEXT(A41,"DDDD") -> domingo | G41: =AVERAGE(Datos!H440:H449) -> 3585 | I41: 0 | J41: 0 | K41: 0 | L41: 0 | M41: 0 | N41: 0 | O41: 1 | P41: 1 | Q41: 1 | R41: 1 | S41: 1 | T41: 0
A42: 45929 | B42: =SUM(Datos!H450:H460) -> 21135 | C42: =COUNTA(Datos!H450:H460) -> 11 | D42: 1 | E42: =SUM(C42+D42) -> 12 | F42: =TEXT(A42,"DDDD") -> lunes | G42: =AVERAGE(Datos!H450:H460) -> 1921.3636 | I42: 0 | J42: 0 | K42: 0 | L42: 0 | M42: 1 | N42: 1 | O42: 1 | P42: 0 | Q42: 0 | R42: 0 | S42: 0 | T42: 0
A43: 45931 | B43: =SUM(Datos!H461:H466) -> 12730 | C43: =COUNTA(Datos!H461:H466) -> 6 | D43: 1 | E43: =SUM(C43+D43) -> 7 | F43: Miercoles | G43: =AVERAGE(Datos!H461:H466) -> 2121.6667 | I43: 0 | J43: 0 | K43: 0 | L43: 0 | M43: 1 | N43: 1 | O43: 0 | P43: 0 | Q43: 0 | R43: 0 | S43: 0 | T43: 0
A44: 45935 | B44: =SUM(Datos!H467:H486) -> 58551 | C44: =COUNTA(Datos!H467:H486) -> 20 | D44: 4 | E44: =SUM(C44+D44) -> 24 | F44: =TEXT(A44,"DDDD") -> domingo | G44: =AVERAGE(Datos!H467:H486) -> 2927.55 | I44: 0 | J44: 0 | K44: 1 | L44: 1 | M44: 1 | N44: 1 | O44: 0 | P44: 1 | Q44: 1 | R44: 1 | S44: 1 | T44: 1
A45: 45936 | B45: =SUM(Datos!H487:H499) -> 33190 | C45: =COUNTA(Datos!H487:H499) -> 13 | D45: 2 | E45: =SUM(C45+D45) -> 15 | F45: =TEXT(A45,"DDDD") -> lunes | G45: =AVERAGE(Datos!H487:H499) -> 2553.0769 | I45: 0 | J45: 0 | K45: 0 | L45: 0 | M45: 0 | N45: 1 | O45: 1 | P45: 0 | Q45: 1 | R45: 1 | S45: 1 | T45: 1
A46: 45937 | B46: =SUM(Datos!H500:H503) -> 10450 | C46: =COUNTA(Datos!H500:H503) -> 4 | D46: 1 | E46: =SUM(C46+D46) -> 5 | F46: =TEXT(A46,"DDDD") -> martes | G46: =AVERAGE(Datos!H500:H503) -> 2612.5 | I46: 1 | J46: 1 | K46: 0 | L46: 0 | M46: 0 | N46: 0 | O46: 0 | P46: 0 | Q46: 0 | R46: 0 | S46: 0 | T46: 0
A47: 45939 | B47: =SUM(Datos!H504:H513) -> 24290 | C47: =COUNTA(Datos!H504:H513) -> 10 | D47: 3 | E47: =SUM(C47+D47) -> 13 | F47: =TEXT(A47,"DDDD") -> jueves | G47: =AVERAGE(Datos!H503:H504) -> 3900 | I47: 0 | J47: 0 | K47: 0 | L47: 0 | M47: 0 | N47: 0 | O47: 0 | P47: 0 | Q47: 1 | R47: 1 | S47: 1 | T47: 1
A48: 45940 | B48: =SUM(Datos!H514:H531) -> 60680 | C48: =COUNTA(Datos!H514:H531) -> 18 | D48: 6 | E48: =SUM(C48+D48) -> 24 | F48: =TEXT(A48,"DDDD") -> viernes | G48: =AVERAGE(Datos!H514:H531) -> 3371.1111 | I48: 1 | J48: 1 | K48: 1 | L48: 1 | M48: 0 | N48: 0 | O48: 0 | P48: 0 | Q48: 0 | R48: 1 | S48: 1 | T48: 1
A49: 45941 | B49: =SUM(Datos!H532:H555) -> 78329 | C49: =COUNTA(Datos!H532:H555) -> 24 | D49: 2 | E49: =SUM(C49+D49) -> 26 | F49: =TEXT(A49,"DDDD") -> sábado | G49: =AVERAGE(Datos!H532:H555) -> 3263.7083 | I49: 1 | J49: 1 | K49: 1 | L49: 1 | M49: 1 | N49: 0 | O49: 0 | P49: 0 | Q49: 0 | R49: 1 | S49: 1 | T49: 1
A50: 45942 | B50: =SUM(Datos!H556:H579) -> 80170 | C50: =COUNTA(Datos!H555:H579) -> 25 | D50: 7 | E50: =SUM(C50+D50) -> 32 | F50: =TEXT(A50,"DDDD") -> domingo | G50: =AVERAGE(Datos!H556:H579) -> 3340.4167 | I50: 1 | J50: 1 | K50: 0 | L50: 0 | M50: 0 | N50: 1 | O50: 1 | P50: 1 | Q50: 1 | R50: 1 | S50: 1 | T50: 1
A51: 45957 | B51: =SUM(Datos!H580:H588) -> 29200 | C51: =COUNTA(Datos!H580:H588) -> 9 | D51: 5 | E51: =SUM(C51+D51) -> 14 | F51: =TEXT(A51,"DDDD") -> lunes | G51: =AVERAGE(Datos!H580:H588) -> 3244.4444 | I51: 0 | J51: 0 | K51: 0 | L51: 0 | M51: 0 | N51: 0 | O51: 0 | P51: 0 | Q51: 1 | R51: 1 | S51: 1 | T51: 1
A52: 45958 | B52: =SUM(Datos!H589:H600) -> 31243 | C52: =COUNTA(Datos!H589:H600) -> 12 | D52: 3 | E52: =SUM(C52+D52) -> 15 | F52: =TEXT(A52,"DDDD") -> martes | G52: =AVERAGE(Datos!H589:H600) -> 2603.5833 | I52: 0 | J52: 0 | K52: 0 | L52: 0 | M52: 0 | N52: 0 | O52: 0 | P52: 0 | Q52: 1 | R52: 1 | S52: 1 | T52: 1
A53: 45959 | B53: =SUM(Datos!H601:H611) -> 25635 | C53: =COUNTA(Datos!H601:H611) -> 11 | D53: 4 | E53: =SUM(C53+D53) -> 15 | F53: Miercoles | G53: =AVERAGE(Datos!H601:H611) -> 2330.4545 | I53: 0 | J53: 0 | K53: 0 | L53: 0 | M53: 0 | N53: 0 | O53: 1 | P53: 0 | Q53: 0 | R53: 1 | S53: 1 | T53: 1
A54: 45960 | B54: =SUM(Datos!H612:H618) -> 22960 | C54: =COUNTA(Datos!H612:H618) -> 7 | D54: 2 | E54: =SUM(C54+D54) -> 9 | F54: =TEXT(A54,"DDDD") -> jueves | G54: =AVERAGE(Datos!H612:H618) -> 3280
A55: 45971 | B55: =SUM(Datos!H619:H630) -> 30480 | C55: =COUNTA(Datos!H619:H630) -> 12 | D55: 0 | E55: =SUM(C55+D55) -> 12 | F55: =TEXT(A55,"DDDD") -> lunes | G55: =AVERAGE(Datos!H619:H630) -> 2540
A56: 45972 | B56: =SUM(Datos!H631:H645) -> 31561 | C56: =COUNTA(Datos!H631:H6342) -> 830 | D56: 1 | E56: =SUM(C56+D56) -> 831 | F56: =TEXT(A56,"DDDD") -> martes | G56: =AVERAGE(Datos!H631:H645) -> 2104.0667
A57: 45973 | B57: =SUM(Datos!H646:H653) -> 21390 | C57: =COUNTA(Datos!H646:H653) -> 8 | D57: 3 | E57: =SUM(C57+D57) -> 11 | F57: Miercoles | G57: =AVERAGE(Datos!H646:H653) -> 2673.75
A58: 45974 | B58: =SUM(Datos!H654:H674) -> 53570 | C58: =COUNTA(Datos!H654:H674) -> 21 | D58: 3 | E58: =SUM(C58+D58) -> 24 | F58: =TEXT(A58,"DDDD") -> jueves | G58: =AVERAGE(Datos!H654:H674) -> 2550.9524
A59: 45978 | B59: =SUM(Datos!H646:H659) -> 35400 | C59: =COUNTA(Datos!H646:H659) -> 14 | D59: 1 | E59: =SUM(C59+D59) -> 15 | F59: =TEXT(A59,"DDDD") -> lunes | G59: =AVERAGE(Datos!H620:H631) -> 2509.1667
A60: 45979 | B60: =SUM(Datos!H660:H664) -> 14430 | C60: =COUNTA(Datos!H660:H664) -> 5 | D60: 2 | E60: =SUM(C60+D60) -> 7 | F60: =TEXT(A60,"DDDD") -> martes | G60: =AVERAGE(Datos!H660:H664) -> 2886
A61: 45980 | B61: =SUM(Datos!H665:H686) -> 51500 | C61: =COUNTA(Datos!H665:H686) -> 22 | D61: 3 | E61: =SUM(C61+D61) -> 25 | F61: Miercoles | G61: =AVERAGE(Datos!H665:H686) -> 2340.9091
A62: 45986 | B62: =SUM(Datos!H716:H723) -> 17020 | C62: =COUNTA(Datos!H716:H723) -> 8 | D62: 1 | E62: =SUM(C62+D62) -> 9 | F62: =TEXT(A62,"DDDD") -> martes | G62: =AVERAGE(Datos!H716:H723) -> 2127.5
A63: 45989 | B63: =SUM(Datos!H724:H730) -> 21440 | C63: =COUNTA(Datos!H724:H730) -> 7 | D63: 1 | E63: =SUM(C63+D63) -> 8 | F63: =TEXT(A63,"DDDD") -> viernes | G63: =AVERAGE(Datos!H724:H730) -> 3062.8571
A64: 45990 | B64: =SUM(Datos!H731:H751) -> 74729.4 | C64: =COUNTA(Datos!H731:H751) -> 21 | D64: 2 | E64: =SUM(C64+D64) -> 23 | F64: =TEXT(A64,"DDDD") -> sábado | G64: =AVERAGE(Datos!H731:H751) -> 3558.5429
A65: 45991 | B65: =SUM(Datos!H752:H759) -> 17733 | C65: =COUNTA(Datos!H752:H759) -> 8 | D65: 2 | E65: =SUM(C65+D65) -> 10 | F65: =TEXT(A65,"DDDD") -> domingo | G65: =AVERAGE(Datos!H752:H759) -> 2216.625
A66: 45994 | B66: =SUM(Datos!H760:H762) -> 6540 | C66: =COUNTA(Datos!H760:H762) -> 3 | D66: 1 | E66: =SUM(C66+D66) -> 4 | F66: Miercoles | G66: =AVERAGE(Datos!H760:H762) -> 2180
A67: 45995 | B67: =SUM(Datos!H763:H774) -> 33103.6 | C67: =COUNTA(Datos!H763:H774) -> 12 | D67: 2 | E67: =SUM(C67+D67) -> 14 | F67: =TEXT(A67,"DDDD") -> jueves | G67: =AVERAGE(Datos!H763:H774) -> 2758.6333
A68: 46000 | B68: =SUM(Datos!H775:H780) -> 13503.6 | C68: =COUNTA(Datos!H775:H780) -> 6 | D68: 1 | E68: =SUM(C68+D68) -> 7 | F68: =TEXT(A68,"DDDD") -> martes | G68: =AVERAGE(Datos!H775:H780) -> 2250.6
A69: 46003 | B69: =SUM(Datos!H695:H714) -> 48110 | C69: =COUNTA(Datos!H695:H714) -> 20 | D69: 1 | E69: =SUM(C69+D69) -> 21 | F69: =TEXT(A69,"DDDD") -> viernes | G69: =AVERAGE(Datos!H695:H714) -> 2405.5
A70: 46004 | B70: =SUM(Datos!H736:H752) -> 59523 | C70: =COUNTA(Datos!H736:H752) -> 17 | D70: 3 | E70: =SUM(C70+D70) -> 20 | F70: =TEXT(A70,"DDDD") -> sábado | G70: =AVERAGE(Datos!H736:H752) -> 3501.3529
A71: 46006 | B71: =SUM(Datos!H753:H758) -> 12681 | C71: =COUNTA(Datos!H753:H758) -> 6 | D71: 1 | E71: =SUM(C71+D71) -> 7 | F71: =TEXT(A71,"DDDD") -> lunes | G71: =AVERAGE(Datos!H753:H758) -> 2113.5
A72: 46008 | B72: =SUM(Datos!H824:H829) -> 13650 | C72: =COUNTA(Datos!H824:H829) -> 6 | D72: 0 | E72: =SUM(C72+D72) -> 6 | F72: Miercoles | G72: =AVERAGE(Datos!H824:H829) -> 2275
A73: 46009 | B73: =SUM(Datos!H830:H840) -> 19720 | C73: =COUNTA(Datos!H830:H840) -> 11 | D73: 3 | E73: =SUM(C73+D73) -> 14 | F73: =TEXT(A73,"DDDD") -> jueves | G73: =AVERAGE(Datos!H830:H840) -> 1792.7273
A74: 46013 | B74: =SUM(Datos!H841:H849) -> 32170 | C74: =COUNTA(Datos!H841:H849) -> 9 | D74: 2 | E74: =SUM(C74+D74) -> 11 | F74: =TEXT(A74,"DDDD") -> lunes | G74: =AVERAGE(Datos!H841:H849) -> 3574.4444
A75: 46014 | B75: =SUM(Datos!H850:H863) -> 39226 | C75: =COUNTA(Datos!H850:H863) -> 14 | D75: 3 | E75: =SUM(C75+D75) -> 17 | F75: =TEXT(A75,"DDDD") -> martes | G75: =AVERAGE(Datos!H850:H863) -> 2801.8571
A76: 46015 | B76: =SUM(Datos!H864:H880) -> 44270 | C76: =COUNTA(Datos!H864:H880) -> 17 | D76: 3 | E76: =SUM(C76+D76) -> 20 | F76: Miercoles | G76: =AVERAGE(Datos!H864:H880) -> 2604.1176
A77: 46016 | B77: =SUM(Datos!H881:H894) -> 54770 | C77: =COUNTA(Datos!H881:H894) -> 14 | D77: 5 | E77: =SUM(C77+D77) -> 19 | F77: =TEXT(A77,"DDDD") -> jueves | G77: =AVERAGE(Datos!H881:H894) -> 3912.1429
A78: 46018 | B78: =SUM(Datos!H895:H909) -> 47517 | C78: =COUNTA(Datos!H895:H909) -> 15 | D78: 1 | E78: =SUM(C78+D78) -> 16 | F78: =TEXT(A78,"DDDD") -> sábado | G78: =AVERAGE(Datos!H895:H909) -> 3167.8
A79: 46019 | B79: =SUM(Datos!H910:H921) -> 52800 | C79: =COUNTA(Datos!H910:H921) -> 12 | D79: 5 | E79: =SUM(C79+D79) -> 17 | F79: =TEXT(A79,"DDDD") -> domingo | G79: =AVERAGE(Datos!H910:H921) -> 4400
A80: 46020 | B80: =SUM(Datos!H922:H926) -> 9377 | C80: =COUNTA(Datos!H922:H926) -> 5 | D80: 1 | E80: =SUM(C80+D80) -> 6 | F80: =TEXT(A80,"DDDD") -> lunes | G80: =AVERAGE(Datos!H922:H926) -> 1875.4
A81: 46021 | B81: =SUM(Datos!H927:H929) -> 12080 | C81: =COUNTA(Datos!H927:H929) -> 3 | D81: 1 | E81: =SUM(C81+D81) -> 4 | F81: =TEXT(A81,"DDDD") -> martes | G81: =AVERAGE(Datos!H927:H929) -> 4026.6667
A82: 46022 | B82: =SUM(Datos!H930:H934) -> 17080 | C82: =COUNTA(Datos!H930:H934) -> 5 | D82: 1 | E82: =SUM(C82+D82) -> 6 | F82: Miercoles | G82: =AVERAGE(Datos!H930:H934) -> 3416
A83: 46023 | B83: =SUM(Datos!H935:H956) -> 55560 | C83: =COUNTA(Datos!H935:H956) -> 22 | D83: 2 | E83: =SUM(C83+D83) -> 24 | F83: =TEXT(A83,"DDDD") -> jueves | G83: =AVERAGE(Datos!H935:H956) -> 2525.4545
A84: 46024 | B84: =SUM(Datos!H957:H962) -> 21710 | C84: =COUNTA(Datos!H957:H962) -> 6 | D84: 2 | E84: =SUM(C84+D84) -> 8 | F84: =TEXT(A84,"DDDD") -> viernes | G84: =AVERAGE(Datos!H957:H962) -> 3618.3333
A85: 46025 | B85: =SUM(Datos!H963:H972) -> 18931 | C85: =COUNTA(Datos!H963:H972) -> 10 | D85: 2 | E85: =SUM(C85+D85) -> 12 | F85: =TEXT(A85,"DDDD") -> sábado | G85: =AVERAGE(Datos!H963:H972) -> 1893.1
A86: 46026 | B86: =SUM(Datos!H973:H976) -> 14460 | C86: =COUNTA(Datos!H973:H976) -> 4 | D86: 1 | E86: =SUM(C86+D86) -> 5 | F86: =TEXT(A86,"DDDD") -> domingo | G86: =AVERAGE(Datos!H973:H976) -> 3615
A87: 46027 | B87: =SUM(Datos!H977:H984) -> 25010 | C87: =COUNTA(Datos!H977:H984) -> 8 | D87: 2 | E87: =SUM(C87+D87) -> 10 | F87: =TEXT(A87,"DDDD") -> lunes | G87: =AVERAGE(Datos!H977:H984) -> 3126.25
A88: 46028 | B88: =SUM(Datos!H985:H994) -> 25870 | C88: =COUNTA(Datos!H985:H994) -> 10 | D88: 2 | E88: =SUM(C88+D88) -> 12 | F88: =TEXT(A88,"DDDD") -> martes | G88: =AVERAGE(Datos!H985:H994) -> 2587
A89: 46029 | B89: =SUM(Datos!H995:H1010) -> 46900 | C89: =COUNTA(Datos!H995:H1010) -> 16 | D89: 3 | E89: =SUM(C89+D89) -> 19 | F89: Miercoles | G89: =AVERAGE(Datos!H995:H1010) -> 2931.25
A90: 46030 | B90: =SUM(Datos!H1011:H1034) -> 62281 | C90: =COUNTA(Datos!H1011:H1034) -> 24 | D90: 3 | E90: =SUM(C90+D90) -> 27 | F90: =TEXT(A90,"DDDD") -> jueves | G90: =AVERAGE(Datos!H1011:H1034) -> 2595.0417
A91: 46031 | B91: =SUM(Datos!H1035:H1038) -> 7270 | C91: =COUNTA(Datos!H1035:H1038) -> 4 | D91: 0 | E91: =SUM(C91+D91) -> 4 | F91: =TEXT(A91,"DDDD") -> viernes | G91: =AVERAGE(Datos!H1035:H1038) -> 1817.5
C98: =SUM(C8,C12,C17,C19,C26,C32,C41,C44,C50,C65,C79) -> 172 | D98: =SUM(D8,D12,D17,D19,D26,D32,D41,D44,D50,D65,D79) -> 37
C99: =SUM(C98:D98) -> 209
C101: =SUM(C5,C9,C15,C18,C22,C29,C35,C39,C43,C53,C57,C61,C66,C72,C76,C82,C89) -> 181 | D101: =SUM(E5,E9,E15,E18,E29,E22,E35,E39,E43,E53,E57,E61,E66,E72,E76,E82,E84,E89) -> 220

Sheet KPIs
A1: Métrica | B1: Valor
A2: Total Ingresos | B2: =SUM(Resumen_por_dia!B2:B90) -> 2797924.5
A3: Cantidad Pedidos | B3: =COUNTA(Datos!H2:H934) -> 931
A4: Ticket Promedio | B4: =AVERAGE(Datos!H2:H934) -> 2735.5956

Sheet Hoja1
A1: mes | B1: ingresos | C1: Dias Registrados
A2: Julio | B2: =SUM(Resumen_por_dia!B2:B5) -> 94827 | C2: =COUNTA(Resumen_por_dia!B2:B5) -> 4
A3: Agosto | B3: =SUM(Resumen_por_dia!B6:B19) -> 564881.88 | C3: =COUNTA(Resumen_por_dia!B6:B19) -> 14
A4: Septiembre | B4: =SUM(Resumen_por_dia!B20:B42) -> 514691 | C4: =COUNTA(Resumen_por_dia!B20:B42) -> 23
A5: Octubre | B5: =SUM(Resumen_por_dia!B43:B54) -> 467428 | C5: =COUNTA(Resumen_por_dia!B43:B54) -> 12
A6: Noviembre | B6: =SUM(Resumen_por_dia!B55:B65) -> 369253.4 | C6: =COUNTA(Resumen_por_dia!B54:B61) -> 8
A7: Diciembre | B7: =SUM(Resumen_por_dia!B66:B82) -> 516121.2 | C7: =COUNTA(Resumen_por_dia!B66:B82) -> 17
A8: Enero
A9: Febrero
A10: Marzo
A11: Abril
A12: Mayo
A13: Junio
A14: Julio
A15: Agosto
A16: Septiembre
A17: Octubre
A18: Noviembre
A19: Diciembre

Sheet Resumen_por_hora
A1: Fecha | B1: Hora_24h | C1: Total_Ingresos | D1: Cant_Pedidos
A2: 20 Agosto | B2: 16:21 | C2: 1980 | D2: 1
A3: 20 Agosto | B3: 16:54 | C3: 2720 | D3: 1
A4: 20 Agosto | B4: 17:20 | C4: 4120 | D4: 1
A5: 20 Agosto | B5: 17:50 | C5: 1620 | D5: 1
A6: 20 Agosto | B6: 18:11 | C6: 1260 | D6: 1
A7: 20 Agosto | B7: 18:33 | C7: 2240 | D7: 1
A8: 20 Agosto | B8: 18:47 | C8: 1261 | D8: 1
A9: 20 Agosto | B9: 19:23 | C9: 2840 | D9: 1
A10: 20 Agosto | B10: 19:37 | C10: 1260 | D10: 1
A11: 20 Agosto | B11: 20:18 | C11: 3900 | D11: 1
A12: 20 Agosto | B12: 20:27 | C12: 1790 | D12: 1
A13: 20 Agosto | B13: 20:58 | C13: 3240 | D13: 1
... A35: 21 Agosto | B35: 16:36 | C35: 1740 | D35: 1
